run_tab.py
tui.py
tinyra-0.2.0.dist-info/METADATA
tinyra-0.2.0.dist-info/WHEEL
tinyra-0.2.0.dist-info/entry_points.txt
tinyra-0.2.0.dist-info/top_level.txt
tinyra-0.2.0.dist-info/RECORD
