Metadata-Version: 2.1
Name: tinyra
Version: 0.2.0
Summary: A minimalistic research assistant built with AutoGen.
Requires-Dist: textual
